jsalve/__init__.py
jsalve/error_utils.py
jsalve/utils.py
jsalve-0.1.0b3.dist-info/DESCRIPTION.rst
jsalve-0.1.0b3.dist-info/METADATA
jsalve-0.1.0b3.dist-info/RECORD
jsalve-0.1.0b3.dist-info/WHEEL
jsalve-0.1.0b3.dist-info/metadata.json
jsalve-0.1.0b3.dist-info/top_level.txt
