Metadata-Version: 2.0
Name: jsalve
Version: 0.1.0b3
Summary: JSON API utilities for Python applications.
Home-page: https://github.com/symfonico/jsalve
Author: Julio Gonzalez Altamirano
Author-email: devjga@gmail.com
License: MIT
Keywords: django rest json json-api jsonapi
Platform: Any
Classifier: Development Status :: 4 - Beta
Classifier: Intended Audience :: Developers
Classifier: License :: OSI Approved :: MIT License
Classifier: Natural Language :: English
Classifier: Operating System :: OS Independent
Classifier: Programming Language :: Python :: 3 :: Only
Requires-Dist: django
Requires-Dist: inflection
